kanizsa/__init__.py
kanizsa/kanizsa.py
kanizsa-0.0.1.dist-info/LICENSE
kanizsa-0.0.1.dist-info/METADATA
kanizsa-0.0.1.dist-info/WHEEL
kanizsa-0.0.1.dist-info/top_level.txt
kanizsa-0.0.1.dist-info/RECORD
